butterflymx/__init__.py
butterflymx/butterflymx.py
butterflymx/graphql/__init__.py
butterflymx/graphql/query_builder.py
butterflymx/models/__init__.py
butterflymx/models/butterflymx.py
butterflymx/models/login.py
butterflymx/py.typed
butterflymx/request_client.py
butterflymx/utils.py
butterflymx-0.1.3.dist-info/LICENSE
butterflymx-0.1.3.dist-info/METADATA
butterflymx-0.1.3.dist-info/WHEEL
butterflymx-0.1.3.dist-info/RECORD
