Metadata-Version: 2.1
Name: butterflymx
Version: 0.1.3
Summary: A reverse-engineered ButterflyMX app API wrapper
Home-page: https://github.com/Iapetus-11/ButterflyMX
Keywords: butterflymx,butterflymx-api,butterflymx-graphql
Author: Milo Weinberg
Author-email: iapetus011@gmail.com
Requires-Python: >=3.10,<4.0
Classifier: Programming Language :: Python :: 3
Classifier: Programming Language :: Python :: 3.10
Classifier: Programming Language :: Python :: 3.11
Requires-Dist: aiohttp (>=3.8.4,<4.0.0)
Requires-Dist: beautifulsoup4 (>=4.12.2,<5.0.0)
Requires-Dist: ruff (>=0.0.265,<0.0.266)
Project-URL: Repository, https://github.com/Iapetus-11/ButterflyMX
